AioHTTPLibrary/AioHTTPLibrary.py
AioHTTPLibrary/__init__.py
AioHTTPLibrary/version.py
rf_aiohttplibrary-1.1a8.dist-info/LICENSE
rf_aiohttplibrary-1.1a8.dist-info/METADATA
rf_aiohttplibrary-1.1a8.dist-info/WHEEL
rf_aiohttplibrary-1.1a8.dist-info/top_level.txt
rf_aiohttplibrary-1.1a8.dist-info/RECORD
