Metadata-Version: 2.1
Name: rf-aiohttplibrary
Version: 1.1a8
Summary: Test Library for AIO HTTP Calls.
Home-page: https://github.com/joshuariveramnltech/rf-aiohttplibrary
Author: Joshua Kim Rivera
Author-email: joshuakimrivera@gmail.com
License: Type license() to see the full license text
Platform: any
Classifier: Development Status :: 4 - Beta
Classifier: License :: OSI Approved :: MIT License
Classifier: Operating System :: OS Independent
Classifier: Programming Language :: Python :: 3
Classifier: Topic :: Software Development :: Testing
Classifier: Framework :: Robot Framework
Classifier: Framework :: Robot Framework :: Library
Requires-Dist: aiodns (==2.0.0)
Requires-Dist: aiohttp (==3.7.3)
Requires-Dist: robotframework (>=3.2.2)
Requires-Dist: robotframework-pythonlibcore (>=2.1.0)
